{"encoder_version": {"cmdline": ["ffmpeg", "-nostats", "-loglevel", "error", "-y", "-r", "50", "-f", "rawvideo", "-s:v", "600x400", "-pix_fmt", "rgb24", "-i", "-", "-vcodec", "libx264", "-pix_fmt", "yuv420p", "/Users/francis/Dropbox/Postdoc/code/git/frsong/pyrl/training_dir/openaigym.video.0.62594.video000027.mp4"], "version": "ffmpeg version 2.6.3 Copyright (c) 2000-2015 the FFmpeg developers\nbuilt with Apple LLVM version 6.1.0 (clang-602.0.53) (based on LLVM 3.6.0svn)\nconfiguration: --prefix=/usr/local/Cellar/ffmpeg/2.6.3 --enable-shared --enable-pthreads --enable-gpl --enable-version3 --enable-hardcoded-tables --enable-avresample --cc=clang --host-cflags= --host-ldflags= --enable-libx264 --enable-libmp3lame --enable-libvo-aacenc --enable-libxvid --enable-vda\nlibavutil      54. 20.100 / 54. 20.100\nlibavcodec     56. 26.100 / 56. 26.100\nlibavformat    56. 25.101 / 56. 25.101\nlibavdevice    56.  4.100 / 56.  4.100\nlibavfilter     5. 11.102 /  5. 11.102\nlibavresample   2.  1.  0 /  2.  1.  0\nlibswscale      3.  1.101 /  3.  1.101\nlibswresample   1.  1.100 /  1.  1.100\nlibpostproc    53.  3.100 / 53.  3.100\n", "backend": "ffmpeg"}, "content_type": "video/mp4", "episode_id": 27}